extract_env/__init__.py
extract_env/__main__.py
extract_env/abstract.py
extract_env/compose.py
extract_env/env.py
extract_env/envfile.py
extract_env/envlist.py
extract_env/main.py
extract_env/utils.py
extract_env/yaml_io.py
extract_env-0.1.0.dist-info/LICENCE.md
extract_env-0.1.0.dist-info/METADATA
extract_env-0.1.0.dist-info/WHEEL
extract_env-0.1.0.dist-info/entry_points.txt
extract_env-0.1.0.dist-info/RECORD
