Metadata-Version: 2.1
Name: extract-env
Version: 0.1.0
Summary: Moves the environment variables from a docker compose file into a .env file.
License: MIT
Author: Zack Hankin
Author-email: admin@hankin.io
Requires-Python: >=3.11,<4.0
Classifier: License :: OSI Approved :: MIT License
Classifier: Operating System :: OS Independent
Classifier: Programming Language :: Python :: 3
Classifier: Programming Language :: Python :: 3.11
Classifier: Programming Language :: Python :: 3.12
Requires-Dist: click (>=8.1.7,<9.0.0)
Requires-Dist: ruamel-yaml (>=0.18.6,<0.19.0)
